
[TOC]

### Java bytecode - Java 字节码
- Java 代码编译后中间代码格式
- JVM 指令集，是 JVM 执行的指令格式
- 由单字节 byte 的指令组成，理论上最多支持256个操作码 opcode

操作码 opcode - 指令
- 由`类型前缀`和`操作名称`两部分组成
- 根据指令的性质分类：
    1. 栈操作指令（包括与局部变量交互的指令）
    2. 程序流控制指令
    3. 对象操作指令（包括方法调用指令）
    4. 算术运算及类型转换指令
    5. 其他专门任务指令（如同步指令或抛异常指令等）

### 创建一个简单的 Java 类 HelloBytecode.java
```java
package com.xtransformers;

public class HelloBytecode {
    public static void main(String[] args) {
        HelloBytecode obj = new HelloBytecode();
    }
}
```

### 编译

```bash
javac -d . HelloBytecode.java
```

javac 工具默认开启了优化功能，生成的字节码中没有局部变量表 LocalVariableTable，相当于局部变量名称被擦除。如果需要这些调试信息，在编译时增加 `-g` 选项。

### 反编译，获取字节码清单

```bash
# 使用包名或相对路径都可以
javap -c com.xtransformers.HelloBytecode
javap -c com/xtransformers/HelloBytecode
javap -c com/xtransformers/HelloBytecode.class

Compiled from "HelloBytecode.java"
public class com.xtransformers.HelloBytecode {
  public com.xtransformers.HelloBytecode();
    Code:
       0: aload_0
       1: invokespecial #1                  // Method java/lang/Object."<init>":()V
       4: return

  public static void main(java.lang.String[]);
    Code:
       0: new           #2                  // class com/xtransformers/HelloBytecode
       3: dup
       4: invokespecial #3                  // Method "<init>":()V
       7: astore_1
       8: return
}
```

### 解读字节码清单

有2个方法，一个是默认生成的空参构造方法，一个是 main 方法。

空参构造方法，默认调用父类构造方法，即执行 `super()` 调用：
```bash
  public com.xtransformers.HelloBytecode();
    Code:
       0: aload_0
       1: invokespecial #1                  // Method java/lang/Object."<init>":()V
       4: return
```

### 常量池 Constant Pool

反编译时，指定 `-verbose` 选项，输出附加信息：

```bash
javap -c -verbose com/xtransformers/HelloBytecode.class

Classfile /com/xtransformers/HelloBytecode.class
  Last modified Jul 4, 2021; size 451 bytes
  MD5 checksum 82824382cbc54ccd9199efa4866016c1
  Compiled from "HelloBytecode.java"
public class com.xtransformers.HelloBytecode
  minor version: 0
  major version: 52
  flags: ACC_PUBLIC, ACC_SUPER
Constant pool:
   #1 = Methodref          #4.#19         // java/lang/Object."<init>":()V
   #2 = Class              #20            // com/xtransformers/HelloBytecode
   #3 = Methodref          #2.#19         // com/xtransformers/HelloBytecode."<init>":()V
   #4 = Class              #21            // java/lang/Object
   #5 = Utf8               <init>
   #6 = Utf8               ()V
   #7 = Utf8               Code
   #8 = Utf8               LineNumberTable
   #9 = Utf8               LocalVariableTable
  #10 = Utf8               this
  #11 = Utf8               Lcom/xtransformers/HelloBytecode;
  #12 = Utf8               main
  #13 = Utf8               ([Ljava/lang/String;)V
  #14 = Utf8               args
  #15 = Utf8               [Ljava/lang/String;
  #16 = Utf8               obj
  #17 = Utf8               SourceFile
  #18 = Utf8               HelloBytecode.java
  #19 = NameAndType        #5:#6          // "<init>":()V
  #20 = Utf8               com/xtransformers/HelloBytecode
  #21 = Utf8               java/lang/Object
{
  public com.xtransformers.HelloBytecode();
    descriptor: ()V
    flags: ACC_PUBLIC
    Code:
      stack=1, locals=1, args_size=1
         0: aload_0
         1: invokespecial #1                  // Method java/lang/Object."<init>":()V
         4: return
      LineNumberTable:
        line 3: 0
      LocalVariableTable:
        Start  Length  Slot  Name   Signature
            0       5     0  this   Lcom/xtransformers/HelloBytecode;

  public static void main(java.lang.String[]);
    descriptor: ([Ljava/lang/String;)V
    flags: ACC_PUBLIC, ACC_STATIC
    Code:
      stack=2, locals=2, args_size=1
         0: new           #2                  // class com/xtransformers/HelloBytecode
         3: dup
         4: invokespecial #3                  // Method "<init>":()V
         7: astore_1
         8: return
      LineNumberTable:
        line 5: 0
        line 6: 8
      LocalVariableTable:
        Start  Length  Slot  Name   Signature
            0       9     0  args   [Ljava/lang/String;
            8       1     1   obj   Lcom/xtransformers/HelloBytecode;
}
SourceFile: "HelloBytecode.java"
```

编译时间、MD5校验和、源文件、JDK版本等信息。


参考资料：https://www.jrebel.com/blog/java-bytecode-tutorial

